CHANGELOG.md
CITATION.cff
LICENSES/CC-BY-4.0.txt
LICENSES/CC0-1.0.txt
LICENSES/MIT.txt
pyswh/__init__.py
pyswh/errors.py
pyswh/swh.py
pyswh-0.1.0.dist-info/LICENSES/MIT.txt
pyswh-0.1.0.dist-info/LICENSES/CC0-1.0.txt
pyswh-0.1.0.dist-info/LICENSES/CC-BY-4.0.txt
pyswh-0.1.0.dist-info/LICENSE.md
pyswh-0.1.0.dist-info/WHEEL
pyswh-0.1.0.dist-info/METADATA
pyswh-0.1.0.dist-info/RECORD
