Metadata-Version: 2.1
Name: pyswh
Version: 0.1.0
Summary: A Python wrapper for the Software Heritage API
Home-page: https://github.com/sdruskat/pyswh
License: MIT
Keywords: Software Heritage,archive,API
Author: Stephan Druskat
Author-email: pyswh@sdruskat.net
Requires-Python: >=3.8,<4.0
Classifier: Development Status :: 3 - Alpha
Classifier: Intended Audience :: Developers
Classifier: Intended Audience :: Science/Research
Classifier: License :: OSI Approved :: MIT License
Classifier: Operating System :: OS Independent
Classifier: Programming Language :: Python
Classifier: Programming Language :: Python :: 3
Classifier: Programming Language :: Python :: 3.8
Classifier: Programming Language :: Python :: 3.9
Classifier: Programming Language :: Python :: 3.10
Classifier: Topic :: Database
Classifier: Topic :: Scientific/Engineering
Classifier: Topic :: Scientific/Engineering :: Information Analysis
Classifier: Topic :: Software Development :: Libraries
Classifier: Topic :: Software Development :: Version Control :: Git
Classifier: Topic :: System :: Archiving
Classifier: Topic :: System :: Software Distribution
Requires-Dist: requests (>=2.28.1,<3.0.0)
Project-URL: Documentation, https://pyswh.readthedocs.io
Project-URL: Repository, https://github.com/sdruskat/pyswh
